rectree/__init__.py
rectree/rectree.ini
rectree/rectree.py
rectree/rectree_config_gui.py
rectree/taskchecker-traced.ico
rectree/taskchecker.ico
rectree_digfish-0.0.1rc0.dist-info/LICENSE
rectree_digfish-0.0.1rc0.dist-info/METADATA
rectree_digfish-0.0.1rc0.dist-info/WHEEL
rectree_digfish-0.0.1rc0.dist-info/top_level.txt
rectree_digfish-0.0.1rc0.dist-info/RECORD
