Metadata-Version: 2.1
Name: rectree-digfish
Version: 0.0.1rc0
Summary: System Tray menu that notifies and keeps you up with the last file changes in a directory
Home-page: https://github.com/digfish/rectree
Author: digfish
Author-email: pescadordigital@gmail.com
License: UNKNOWN
Project-URL: Bug Tracker, https://github.com/digfish/rectree/issues
Platform: UNKNOWN
Classifier: Programming Language :: Python :: 3
Classifier: License :: OSI Approved :: GNU General Public License v3 (GPLv3)
Classifier: Environment :: Win32 (MS Windows)
Classifier: Development Status :: 3 - Alpha
Requires-Python: >=3.7
License-File: LICENSE
